llama_index/readers/dad_jokes/__init__.py
llama_index/readers/dad_jokes/base.py
llama_index_readers_dad_jokes-0.4.1.dist-info/METADATA
llama_index_readers_dad_jokes-0.4.1.dist-info/WHEEL
llama_index_readers_dad_jokes-0.4.1.dist-info/licenses/LICENSE
llama_index_readers_dad_jokes-0.4.1.dist-info/RECORD
