Metadata-Version: 2.4
Name: llama-index-readers-dad-jokes
Version: 0.4.1
Summary: llama-index readers dad_jokes integration
Author-email: Your Name <you@example.com>
Maintainer: sidu
License-Expression: MIT
License-File: LICENSE
Keywords: dad jokes,jokes
Requires-Python: <4.0,>=3.9
Requires-Dist: llama-index-core<0.15,>=0.13.0
